quickerDebug/__init__.py
quickerDebug/quickerDebug.py
quickerDebug-0.1.4.dist-info/LICENSE
quickerDebug-0.1.4.dist-info/METADATA
quickerDebug-0.1.4.dist-info/WHEEL
quickerDebug-0.1.4.dist-info/top_level.txt
quickerDebug-0.1.4.dist-info/RECORD
