Metadata-Version: 2.1
Name: quickerDebug
Version: 0.1.4
Summary: Instant debugger alternative for python
Home-page: https://github.com/GauthamV6002/quickDebug
Author: Gautham Venkateshwaran
Author-email: gauthamv6002@gmail.com
Classifier: Programming Language :: Python :: 3
Classifier: License :: OSI Approved :: MIT License
Classifier: Operating System :: OS Independent
Requires-Python: >=3.8.0
License-File: LICENSE
